lins_cieloApi3/__init__.py
lins_cieloApi3/address.py
lins_cieloApi3/cieloEcommerce.py
lins_cieloApi3/creditCard.py
lins_cieloApi3/customer.py
lins_cieloApi3/debitCard.py
lins_cieloApi3/environment.py
lins_cieloApi3/merchant.py
lins_cieloApi3/objectJSON.py
lins_cieloApi3/payment.py
lins_cieloApi3/recurrentPayment.py
lins_cieloApi3/sale.py
lins_cieloApi3/request/__init__.py
lins_cieloApi3/request/base.py
lins_cieloApi3/request/cardBin.py
lins_cieloApi3/request/createCardToken.py
lins_cieloApi3/request/createSale.py
lins_cieloApi3/request/deactivateRecorrency.py
lins_cieloApi3/request/queryRecorrency.py
lins_cieloApi3/request/querySale.py
lins_cieloApi3/request/reactivateRecorrency.py
lins_cieloApi3/request/updateSale.py
lins_cieloApi3-0.1.3.14.dist-info/METADATA
lins_cieloApi3-0.1.3.14.dist-info/WHEEL
lins_cieloApi3-0.1.3.14.dist-info/top_level.txt
lins_cieloApi3-0.1.3.14.dist-info/RECORD
