Metadata-Version: 2.1
Name: lins-cieloApi3
Version: 0.1.3.14
Summary: Pacote customizado da sdk python da cielo, https://github.com/DeveloperCielo/API-3.0-Python
Home-page: https://bitbucket.org/grupolinsferrao/pypck-lins-cieloapi3/
Author: Halyson Sampaio
Author-email: halyson@lojaspompeia.com.br
License: MIT
Platform: UNKNOWN
